{
	"type": "FeatureCollection",
	"features": [
		{
			"type": "Feature",
			"geometry": {
				"type": "Point",
				"coordinates": [121.5188842, 25.0314006]
			},
			"properties": {
				"機構名稱": "財團法人臺北市敦安社會福利基金會",
				"行政區": "中正區",
				"聯絡人姓名": "",
				"地址": "臺北市10074羅斯福路一段28號10樓",
				"電話": "02-3393-2225",
				"傳真": "02-3393-8937",
				"網址": ""
			}
		},
		{
			"type": "Feature",
			"geometry": {
				"type": "Point",
				"coordinates": [121.5195614, 25.0461973]
			},
			"properties": {
				"機構名稱": "財團法人天主教善牧社會福利基金會",
				"行政區": "中正區",
				"聯絡人姓名": "",
				"地址": "臺北市10041中山北路一段2號11樓之1100",
				"電話": "(02)23815402",
				"傳真": "02-23611371",
				"網址": "http://www.goodshepherd.org.tw/index.html"
			}
		},
		{
			"type": "Feature",
			"geometry": {
				"type": "Point",
				"coordinates": [121.5450011, 25.0812499]
			},
			"properties": {
				"機構名稱": "財團法人張老師基金會",
				"行政區": "中山區",
				"聯絡人姓名": "劉玫伶",
				"地址": "臺北市10482大直街20巷-18號之401",
				"電話": "02-2502-5858",
				"傳真": "",
				"網址": "http://www.1980.org.tw"
			}
		}
	]
}
